avroc/__init__.py
avroc/avro_common.py
avroc/codec.py
avroc/dataclassgen.py
avroc/files.py
avroc/messages.py
avroc/schema.py
avroc/util.py
avroc/bin/__init__.py
avroc/bin/avroc_cli.py
avroc/codegen/__init__.py
avroc/codegen/astutil.py
avroc/codegen/compiler.py
avroc/codegen/dataclass.py
avroc/codegen/errors.py
avroc/codegen/graph.py
avroc/codegen/read.py
avroc/codegen/resolution.py
avroc/codegen/write.py
avroc/runtime/__init__.py
avroc/runtime/blocks.py
avroc/runtime/encoding.py
avroc/runtime/typetest.py
avroc-0.3.1.dist-info/LICENSE
avroc-0.3.1.dist-info/METADATA
avroc-0.3.1.dist-info/WHEEL
avroc-0.3.1.dist-info/entry_points.txt
avroc-0.3.1.dist-info/top_level.txt
avroc-0.3.1.dist-info/RECORD
