Metadata-Version: 2.1
Name: avroc
Version: 0.3.1
Summary: A library for fast Avro serialization and deserialization
Home-page: UNKNOWN
Author: Spencer Nelson
Author-email: s@spencerwnelson.com
License: MIT License
Platform: UNKNOWN
Classifier: License :: OSI Approved :: MIT License
Classifier: Programming Language :: Python :: 3
Requires-Dist: python-snappy
Requires-Dist: zstandard
Requires-Dist: astunparse ; python_version < "3.9.0"
Provides-Extra: dev
Requires-Dist: pytest ; extra == 'dev'
Requires-Dist: fastavro ; extra == 'dev'
Requires-Dist: flake8 ; extra == 'dev'
Requires-Dist: black ; extra == 'dev'
Requires-Dist: mypy ; extra == 'dev'
Requires-Dist: sphinx ; extra == 'dev'
Provides-Extra: doc
Requires-Dist: sphinx ; extra == 'doc'
